<?xml version="1.0" encoding="UTF-8"?>
<feature
      id="org.csstudio.product.feature"
      label="CS-Studio Product"
      version="3.2.0.qualifier"
      provider-name="CS-Studio Collaboration &lt;cs-studio-core@lists.sourceforge.net&gt;"
      plugin="org.csstudio.product">

   <description url="http://controlsystemstudio.github.io/">
      CS-Studio Product.
   </description>

   <copyright url="http://controlsystemstudio.github.io/">
      Use is subject to license.
   </copyright>

   <license url="http://www.eclipse.org/legal/epl-v10.html">
      Eclipse Public License.
   </license>

   <includes
         id="org.csstudio.trends.databrowser2.feature"
         version="0.0.0"/>

   <requires>
      <import plugin="org.eclipse.core.runtime" version="3.6.0" match="greaterOrEqual"/>
      <import plugin="org.csstudio.data" version="1.0.0" match="greaterOrEqual"/>
      <import plugin="org.csstudio.utility.pv" version="3.0.0" match="greaterOrEqual"/>
      <import plugin="org.csstudio.platform.libs.epics" version="3.1.1" match="greaterOrEqual"/>
      <import plugin="org.eclipse.ui"/>
      <import plugin="org.eclipse.help"/>
      <import plugin="org.eclipse.help.ui"/>
      <import plugin="org.junit" version="4.8.2" match="greaterOrEqual"/>
      <import plugin="org.junit" version="4.8.0" match="greaterOrEqual"/>
      <import plugin="org.csstudio.platform.libs.jdbc" version="1.3.0" match="greaterOrEqual"/>
      <import plugin="org.eclipse.ui.ide" version="3.6.0" match="greaterOrEqual"/>
      <import plugin="org.eclipse.core.filesystem" version="1.3.0" match="greaterOrEqual"/>
      <import plugin="org.eclipse.core.resources"/>
      <import plugin="org.csstudio.openfile" version="3.0.0" match="greaterOrEqual"/>
      <import plugin="org.eclipse.core.runtime" version="3.7.0" match="greaterOrEqual"/>
      <import plugin="org.csstudio.logbook" version="1.1.0" match="greaterOrEqual"/>
      <import plugin="org.csstudio.ui.util" version="3.1.0" match="greaterOrEqual"/>
      <import plugin="com.google.common" version="10.0.1" match="greaterOrEqual"/>
      <import plugin="org.eclipse.core.resources" version="3.7.100" match="greaterOrEqual"/>
      <import plugin="org.csstudio.apputil.ui" version="3.2.0" match="greaterOrEqual"/>
      <import plugin="org.eclipse.core.runtime" version="3.5.0" match="greaterOrEqual"/>
      <import plugin="javax.mail" version="1.4.4" match="greaterOrEqual"/>
      <import plugin="org.eclipse.help" version="3.4.1" match="greaterOrEqual"/>
      <import plugin="org.csstudio.email" version="1.0.0" match="greaterOrEqual"/>
      <import plugin="org.csstudio.apputil.ui" version="1.1.7" match="greaterOrEqual"/>
      <import plugin="org.csstudio.java" version="3.0.0" match="greaterOrEqual"/>
      <import plugin="org.eclipse.equinox.security" version="1.0.0" match="greaterOrEqual"/>
      <import plugin="org.csstudio.apputil" version="3.0.0" match="greaterOrEqual"/>
      <import plugin="org.csstudio.utility.singlesource" version="1.0.0" match="greaterOrEqual"/>
      <import plugin="org.eclipse.osgi" version="3.6.0" match="greaterOrEqual"/>
      <import plugin="org.csstudio.platform.libs.jms" version="1.1.1" match="greaterOrEqual"/>
      <import plugin="org.eclipse.equinox.preferences" version="3.3.0" match="greaterOrEqual"/>
      <import plugin="org.eclipse.jface" version="3.6.0" match="greaterOrEqual"/>
      <import plugin="org.eclipse.ui.workbench" version="3.6.0" match="greaterOrEqual"/>
      <import plugin="org.eclipse.ui.console" version="3.5.0" match="greaterOrEqual"/>
      <import plugin="org.csstudio.logging" version="0.0.1" match="greaterOrEqual"/>
      <import plugin="org.csstudio.utility.pvmanager.vtype" version="2.0.0" match="greaterOrEqual"/>
      <import plugin="org.epics.vtype" version="2.0.0" match="greaterOrEqual"/>
      <import plugin="org.eclipse.ui" version="3.6.0" match="greaterOrEqual"/>
      <import plugin="org.csstudio.csdata" version="3.0.0" match="greaterOrEqual"/>
      <import plugin="org.csstudio.ui.util" version="3.0.0" match="greaterOrEqual"/>
      <import plugin="org.csstudio.ui.menu" version="3.0.0" match="greaterOrEqual"/>
      <import plugin="org.csstudio.workspace" version="3.0.0" match="greaterOrEqual"/>
      <import plugin="org.eclipse.help.webapp"/>
      <import plugin="org.eclipse.core.resources" version="3.6.0" match="greaterOrEqual"/>
      <import plugin="org.eclipse.equinox.security" version="1.0.200" match="greaterOrEqual"/>
      <import plugin="org.csstudio.java" version="3.1.0" match="greaterOrEqual"/>
      <import plugin="org.csstudio.startup" version="3.0.0" match="greaterOrEqual"/>
      <import plugin="org.csstudio.logging" version="3.0.0" match="greaterOrEqual"/>
      <import plugin="org.csstudio.logging.ui" version="3.0.0" match="greaterOrEqual"/>
      <import plugin="org.csstudio.ui.menu.app" version="3.0.0" match="greaterOrEqual"/>
      <import plugin="org.csstudio.security" version="1.0.0" match="greaterOrEqual"/>
      <import plugin="org.csstudio.startup.helper" version="3.1.0" match="greaterOrEqual"/>
      <import plugin="org.csstudio.apputil" version="3.0.1" match="greaterOrEqual"/>
      <import plugin="org.eclipse.help" version="3.5.0" match="greaterOrEqual"/>
      <import plugin="org.csstudio.utility.pvmanager" version="2.0.0" match="greaterOrEqual"/>
      <import plugin="org.epics.util" version="0.2.0" match="greaterOrEqual"/>
      <import plugin="org.epics.util" version="0.2.1" match="greaterOrEqual"/>
      <import plugin="org.eclipse.core.resources" version="3.7.0" match="greaterOrEqual"/>
      <import plugin="org.eclipse.ui.ide" version="3.7.0" match="greaterOrEqual"/>
      <import plugin="org.eclipse.ui.console" version="3.3.0" match="greaterOrEqual"/>
      <import plugin="org.csstudio.ui.util" version="3.2.0" match="greaterOrEqual"/>
      <import plugin="org.eclipse.equinox.security" version="1.1.1" match="greaterOrEqual"/>
      <import plugin="org.eclipse.equinox.util" version="1.0.300" match="greaterOrEqual"/>
      <import plugin="org.eclipse.equinox.ds" version="1.3.1" match="greaterOrEqual"/>
      <import plugin="org.eclipse.core.expressions" version="3.4.300" match="greaterOrEqual"/>
      <import plugin="org.csstudio.autocomplete" version="1.0.0" match="greaterOrEqual"/>
      <import plugin="org.csstudio.logbook" version="3.1.0" match="greaterOrEqual"/>
      <import plugin="org.csstudio.utility.pvmanager.ui" version="3.0.0" match="greaterOrEqual"/>
      <import plugin="org.csstudio.utility.pvmanager.extra" version="3.2.0" match="greaterOrEqual"/>
      <import plugin="org.csstudio.csdata" version="3.2.0" match="greaterOrEqual"/>
      <import plugin="org.epics.vtype" version="2.1.0" match="greaterOrEqual"/>
      <import plugin="org.csstudio.simplepv" version="1.0.0" match="greaterOrEqual"/>
      <import plugin="org.epics.util" version="0.2.2" match="greaterOrEqual"/>
      <import plugin="org.csstudio.utility.pvmanager" version="3.2.0" match="greaterOrEqual"/>
      <import plugin="org.csstudio.utility.pv" version="3.1.0" match="greaterOrEqual"/>
      <import plugin="org.csstudio.utility.product" version="1.1.0" match="greaterOrEqual"/>
      <import plugin="org.epics.pvdata" version="3.0.3" match="greaterOrEqual"/>
      <import plugin="org.epics.pvaccess" version="3.0.5" match="greaterOrEqual"/>
      <import plugin="org.csstudio.platform.libs.epics" version="3.2.0" match="greaterOrEqual"/>
   </requires>

   <plugin
         id="org.csstudio.product"
         download-size="0"
         install-size="0"
         version="0.0.0"
         unpack="false"/>

   <plugin
         id="org.csstudio.startup.intro"
         download-size="0"
         install-size="0"
         version="0.0.0"
         unpack="false"/>

   <plugin
         id="org.csstudio.startup.helper"
         download-size="0"
         install-size="0"
         version="0.0.0"
         unpack="false"/>

   <plugin
         id="org.csstudio.utility.product"
         download-size="0"
         install-size="0"
         version="0.0.0"
         unpack="false"/>

   <plugin
         id="org.csstudio.utility.product.default"
         download-size="0"
         install-size="0"
         version="0.0.0"
         fragment="true"
         unpack="false"/>

</feature>
